{
  "main": {
    "name":"Sardar Shoaib",
    "description":"Confident and creative Graphic designer, Graphics motion(video editing and animation) & UI/UX designer with extensive experience in Adobe Creative Suite over 5-year experience. Self-motivated and knowledgeable of the latest technologies with a strong grip on tools",
    "image":"profile.png",
    "bio":"I am a Computer Scientist who just completed BSCS degree from the Pakistan one of the best IT university Federal urdu university Islamabad in Computer Science. I am a highly skilled professional developer who loves to take on the challenges and then solve them.",
    "contactmessage":"Here is where you should write your message to readers to have them get in contact with you.",
    "email": "Sardarshoaib910@gmail.com",
    "phone": "+923109457915",
    "linktree":"https://linktr.ee/sardarshoaib91",
    "github":"https://linktr.ee/sardarshoaib91",
    "linkedin":"https://www.linkedin.com/in/sardar-shoaib-401a10213/",
    "address":{
      "street":"(Your Street)",
      "city":"Islamabad,",
      "state":"Pakistan",
      "zip": "(Your Zip/Postal Code)"
    },
 
    "social":[
      {
        "name":"linkedin",
        "url":"https://www.linkedin.com/in/sardar-shoaib-401a10213/",
        "className":"fa fa-linkedin"
      },
      {
        "name":"facebook",
        "url":"https://www.facebook.com/sardarshoaib91/",
        "className":"fa fa-facebook"
      },
      {
        "name":"linktree",
        "url":"https://linktr.ee/sardarshoaib91",
        "className":"fa fa-link"
      }
    ]
  },
  "resume":{
    "skillmessage":"My top skills in which I have work on many projects and still working to improve.",
    "education":[
      {

        "school":"Federal urdu University islamabad Pakistan.",
        "degree":"Bechelor of Computer Science",
        "graduated":"2017-2021"
      },
      {
        "school":"Muhammdan Science college Hajira.",
        "degree":"FSC pre engineering.",
        "graduated":"2014-2016"
           }
    ],
    "work":[
      {
        "company":"Rohtas Marketing",
        "title":"Graphics designer || Motion graphics",
        "years":"Nov 2021 - Feb 2022",
        "description":"Working as a Graphics designer || Motion graphics. I have Worked on 2 Chiled companies Designes.'Cygnus Marketing','Rohtas Digital'"
      },
      {
        "company":"5tree digital",
        "title":"Graphics designer || Motion graphics || UI/UX designer",
        "years":"June 2022 - present",
        "description":"Currently Working at 5tree digital company as a Graphics designer || Motion graphics || UI/UX designer, for 'Naseems Accountants(www.naseems.co.uk)'"
      },
      {
        "company":"Freelancing at upwor&fiverr",
        "title":"Graphics designer || Motion graphics || UI/UX designer",
        "years":"Feb 2017 - present",
        "description":"Working on fiverr and upwork with lots of experience, I have worked with many International clients"
      }
    ],
    "skills":[
      {
        "name":"Adobe Photoshop",
        "level":"95%"
      },
      {
        "name":"Adobe Illustrator",
        "level":"80%"
      },
      {
        "name":"Adobe XD (UI/UX)",
        "level":"90%"
      },
      {
        "name":"Figma (UI/UX)",
        "level":"90%"
      },
      {
        "name":"Adobe After Effect",
        "level":"75%"
      },
      {
        "name":"Adobe premier pro",
        "level":"80%"
      },
      {
        "name":"Adobe Character animator",
        "level":"65%"
      },
      {
        "name":"Vyond 2d animator",
        "level":"98%"
      },
      {
        "name":"Wondershare Filmora",
        "level":"90%"
      },
      {
        "name":"HTML/CSS",
        "level":"70%"
      }
    ]
  },
  "portfolio":{
    "projects": [
      {
        "title":"Responsive Websites Design",
        "category":"My Travel Blog for my post-university travels",
        "image":"uiuxport.png",
        "url":"https://www.behance.net/Graphico_ss"
      },
      {
        "title":"Product Design Mobile App",
        "category":"(offline now) A fighting gear company I started",
        "image":"uiuxmobileapp.png",
        "url":"https://www.behance.net/Graphico_ss"
      },
      {
        "title":"Branding Graphics",
        "category":"Website I built for a restaurant I like in Thailand",
        "image":"Branding.PNG",
        "url":"https://www.flickr.com/photos/194288497@N06/"
      },
      {
        "title":"Esports Graphics",
        "category":"A React based resume website template",
        "image":"Esportslogo.PNG",
        "url":"https://dribbble.com/obsarv"
      },
      {
        "title":"Animation & Video Editing",
        "category":"(MVP Only) A React and Meteor based chat University project.",
        "image":"Graphicsmotion.gif",
        "url":"https://drive.google.com/drive/folders/1iBo875OyuBZN0Kwl3IO-j7-qMeTTmchF?usp=share_link"
      },
      {
        "title":"2D Animated Videos",
        "category":"My Travel Blog for my post-university travels",
        "image":"Explainervideos.gif",
        "url":"https://drive.google.com/drive/folders/1iBo875OyuBZN0Kwl3IO-j7-qMeTTmchF?usp=share_link"
      }      
    ]
  }
}
